dotignore/__about__.py
dotignore/__init__.py
dotignore/__main__.py
dotignore/cli.py
dotignore/core.py
dotignore-0.0.2.dist-info/LICENSE
dotignore-0.0.2.dist-info/METADATA
dotignore-0.0.2.dist-info/WHEEL
dotignore-0.0.2.dist-info/entry_points.txt
dotignore-0.0.2.dist-info/top_level.txt
dotignore-0.0.2.dist-info/RECORD
