Metadata-Version: 2.1
Name: dotignore
Version: 0.0.2
Summary: Command line tool to generate ignore files
Home-page: https://github.com/Xvezda/dotignore
Author: Xvezda
Author-email: xvezda@naver.com
License: UNKNOWN
Keywords: git,ignore files,command line tool
Platform: UNKNOWN
Classifier: Development Status :: 2 - Pre-Alpha
Classifier: Environment :: Console
Classifier: License :: OSI Approved :: MIT License
Classifier: Programming Language :: Python :: 2
Classifier: Programming Language :: Python :: 2.7
Classifier: Programming Language :: Python :: 3
Classifier: Programming Language :: Python :: 3.5
Classifier: Programming Language :: Python :: 3.6
Classifier: Programming Language :: Python :: 3.7
Classifier: Programming Language :: Python :: 3.8
Classifier: Topic :: Software Development
Classifier: Topic :: Software Development :: Version Control :: Git
Classifier: Topic :: Terminals
Classifier: Topic :: Utilities
Requires-Dist: requests
